main.py
auto_example_env-0.1.0.dist-info/METADATA
auto_example_env-0.1.0.dist-info/WHEEL
auto_example_env-0.1.0.dist-info/entry_points.txt
auto_example_env-0.1.0.dist-info/top_level.txt
auto_example_env-0.1.0.dist-info/RECORD
