Metadata-Version: 2.4
Name: auto-example-env
Version: 0.1.0
Summary: Generate example.env from .env file for documentation purposes
Requires-Python: >=3.8
